{
    "%vlocity_namespace%__Active__c": true,
    "%vlocity_namespace%__OmniScriptId__c": {
        "Name": "Enroll",
        "VlocityDataPackType": "VlocityMatchingKeyObject",
        "VlocityMatchingRecordSourceKey": "%vlocity_namespace%__OmniScript__c/OSH/Enroll/English",
        "VlocityRecordSObjectType": "%vlocity_namespace%__OmniScript__c"
    },
    "%vlocity_namespace%__ParentElementId__c": {
        "%vlocity_namespace%__OmniScriptId__c": {
            "Name": "Enroll",
            "VlocityDataPackType": "VlocityMatchingKeyObject",
            "VlocityMatchingRecordSourceKey": "%vlocity_namespace%__OmniScript__c/OSH/Enroll/English",
            "VlocityRecordSObjectType": "%vlocity_namespace%__OmniScript__c"
        },
        "Name": "enrollPrograms",
        "VlocityDataPackType": "VlocityMatchingKeyObject",
        "VlocityMatchingRecordSourceKey": "%vlocity_namespace%__Element__c/%vlocity_namespace%__OmniScript__c/OSH/Enroll/English/enrollPrograms",
        "VlocityRecordSObjectType": "%vlocity_namespace%__Element__c"
    },
    "%vlocity_namespace%__ParentElementName__c": "enrollPrograms",
    "%vlocity_namespace%__ParentElementType__c": "Step",
    "%vlocity_namespace%__PropertySet__c": {
        "HTMLTemplateId": "",
        "controlWidth": 12,
        "dataType": "Currency",
        "dateFormat": "MM-dd-yyyy",
        "disOnTplt": false,
        "expression": "IF(%planSelection:selectedPlans|1:PriceDiff% != null &&%planSelection:selectedPlans|1:PriceDiff% != \"\", IF(%planSelection:selectedPlans|1:flagDifference% == true &&  %myFamily:FormulaConForDiplayAddInfo180% == false , %planSelection:selectedPlans|1:PriceDiff% ,%planSelection:selectedPlans|1:Price%),0)",
        "hide": true,
        "hideGroupSep": false,
        "inputWidth": 12,
        "label": "formulaPriceEnrollPrograms",
        "mask": null,
        "show": null,
        "showInputWidth": false
    },
    "%vlocity_namespace%__ReusableOmniScript__c": false,
    "%vlocity_namespace%__Type__c": "Formula",
    "Name": "formulaPriceEnrollPrograms",
    "VlocityDataPackType": "SObject",
    "VlocityRecordSObjectType": "%vlocity_namespace%__Element__c",
    "VlocityRecordSourceKey": "%vlocity_namespace%__Element__c/%vlocity_namespace%__OmniScript__c/OSH/Enroll/English/formulaPriceEnrollPrograms"
}