{
    "": "",
    "ActualTime": 1595,
    "ChargentOrders__ChargentOrder__c_1": [
        {
            "ChargentOrders__Account__c": "0018A00000Uw8dDQAR",
            "ChargentOrders__Billing_Address__c": "Artis Place",
            "ChargentOrders__Billing_City__c": "Toledo",
            "ChargentOrders__Billing_Country__c": "United States",
            "ChargentOrders__Billing_Email__c": "lordsith@mail.com",
            "ChargentOrders__Billing_First_Name__c": "Lord",
            "ChargentOrders__Billing_Last_Name__c": "Zanna",
            "ChargentOrders__Billing_Phone__c": "1341234123",
            "ChargentOrders__Billing_State__c": "OH",
            "ChargentOrders__Billing_Zip_Postal__c": "43605",
            "ChargentOrders__Date__c": "2020-08-05T00:00:00.000Z",
            "ChargentOrders__Payment_Status__c": "Automated Collection",
            "ChargentOrders__Status__c": "Initiated",
            "ChargentOrders__Subtotal__c": 732.73,
            "Id": "a918A0000004SZtQAM",
            "UpsertSuccess": true
        }
    ],
    "CpuTime": 1852,
    "Welcome": {
        "Address": "Artis Place",
        "City": "Toledo",
        "Email": "lordsith@mail.com",
        "FormulaState": true,
        "MessagingStatesoff": true,
        "State": "OH",
        "TAAddressGoogle-Block": {
            "TAAddressGoogle": "Artis Pl, Toledo, OH 43605, USA",
            "address": "Artis Place",
            "buildingSuiteApartment": "12345",
            "city": "Toledo",
            "country": "United States",
            "state": "OH",
            "zipCode": "43605"
        },
        "Telephone": "1341234123",
        "ZipCode": "43605",
        "fname": "Lord",
        "lname": "Sith"
    },
    "error": "OK",
    "responseType": "SObject"
}